{"builtAt":1691757297425,"assets":[{"name":"index.js","size":3154},{"name":"Kit/App/index.js","size":425},{"name":"Kit/DataDisplay/Avatar/index.js","size":147},{"name":"Kit/DataDisplay/Badge/index.js","size":1839},{"name":"Kit/DataDisplay/Card/index.js","size":8989},{"name":"Kit/DataDisplay/Collapse/index.js","size":217},{"name":"Kit/DataDisplay/Image/index.js","size":653},{"name":"Kit/DataDisplay/ItemList/index.js","size":7159},{"name":"Kit/DataDisplay/Tooltip/index.js","size":167},{"name":"Kit/DataDisplay/Tree/index.js","size":4554},{"name":"Kit/DataEntry/Checkbox/index.js","size":147},{"name":"Kit/DataEntry/Input/index.js","size":191},{"name":"Kit/DataEntry/InputNumber/index.js","size":2622},{"name":"Kit/DataEntry/Radio/index.js","size":138},{"name":"Kit/DataEntry/Rate/index.js","size":721},{"name":"Kit/DataEntry/Select/index.js","size":2992},{"name":"Kit/DataEntry/Tag/index.js","size":135},{"name":"Kit/DataEntry/Switch/index.js","size":1939},{"name":"Kit/Feedback/Alert/index.js","size":1456},{"name":"Kit/Feedback/Modal/index.js","size":443},{"name":"Kit/Feedback/Progress/index.js","size":406},{"name":"Kit/Feedback/SnackBar/index.js","size":264},{"name":"Kit/General/Button/index.js","size":8457},{"name":"Kit/General/Typography/index.js","size":233},{"name":"Kit/General/Icon/index.js","size":1027},{"name":"Kit/Layout/Divider/index.js","size":654},{"name":"Kit/Layout/Grid/index.js","size":133},{"name":"Kit/Layout/Space/index.js","size":410},{"name":"Kit/Navigation/Breadcrumb/index.js","size":483},{"name":"Kit/Navigation/DropDown/index.js","size":327},{"name":"Kit/Navigation/Header/index.js","size":3280},{"name":"Kit/Navigation/Menu/index.js","size":137},{"name":"Kit/Navigation/Steps/index.js","size":844},{"name":"Kit/Navigation/Pagination/index.js","size":3214},{"name":"theme/index.js","size":4873},{"name":"theme/typography.js","size":443},{"name":"theme/colors.js","size":1622},{"name":"Kit/DataEntry/Select/style.js","size":8133},{"name":"Kit/Feedback/SnackBar/SnackBarProvider.js","size":375},{"name":"Kit/App/style.js","size":731},{"name":"Kit/DataDisplay/Avatar/Avatar.js","size":794},{"name":"Kit/DataDisplay/Avatar/AvatarGroup.js","size":335},{"name":"Kit/DataDisplay/Card/theme.js","size":986},{"name":"Kit/DataDisplay/Card/ColorBar.js","size":835},{"name":"Kit/DataDisplay/Image/theme.js","size":148},{"name":"Kit/DataEntry/Select/theme.js","size":1440},{"name":"fonts/Inter-roman.var.woff2.js","size":302972},{"name":"fonts/Inter-italic.var.woff2.js","size":326780},{"name":"Kit/DataEntry/Checkbox/Checkbox.js","size":3171},{"name":"Kit/DataEntry/Checkbox/Group.js","size":2111},{"name":"Kit/DataEntry/Input/Input.js","size":4240},{"name":"Kit/DataEntry/Input/TextArea.js","size":3928},{"name":"Kit/DataEntry/Input/Password.js","size":3935},{"name":"Kit/DataEntry/Radio/Group.js","size":2036},{"name":"Kit/DataEntry/Radio/Radio.js","size":3200},{"name":"icons/KitCalendarOutlined.js","size":322},{"name":"icons/KitDeleteOutlined.js","size":318},{"name":"icons/KitDownloadOutlined.js","size":322},{"name":"icons/KitDropdownOutlined.js","size":322},{"name":"icons/KitDropupOutlined.js","size":318},{"name":"icons/KitEditOutlined.js","size":314},{"name":"icons/KitHideOutlined.js","size":314},{"name":"icons/KitInfoOutlined.js","size":314},{"name":"icons/KitLessOutlined.js","size":314},{"name":"icons/KitListOutlined.js","size":314},{"name":"icons/KitLockOutlined.js","size":314},{"name":"icons/KitLogoutOutlined.js","size":318},{"name":"icons/KitPdfOutlined.js","size":312},{"name":"icons/KitPlusOutlined.js","size":314},{"name":"icons/KitRailroadOutlined.js","size":322},{"name":"icons/KitShowOutlined.js","size":314},{"name":"icons/KitWarningOutlined.js","size":320},{"name":"Kit/DataEntry/Tag/Tag.js","size":2563},{"name":"Kit/DataEntry/Tag/TagInput.js","size":2339},{"name":"Kit/DataEntry/Switch/theme.js","size":825},{"name":"Kit/General/Button/theme.js","size":7762},{"name":"Kit/General/Typography/Title.js","size":1870},{"name":"Kit/General/Typography/Text.js","size":1032},{"name":"Kit/General/Typography/Link.js","size":1018},{"name":"Kit/General/Typography/Paragraph.js","size":1023},{"name":"Kit/General/Icon/theme.js","size":305},{"name":"Kit/Layout/Grid/Row.js","size":130},{"name":"Kit/Layout/Grid/Col.js","size":130},{"name":"Kit/Layout/Space/theme.js","size":81},{"name":"Kit/Feedback/Modal/Modal.js","size":3598},{"name":"Kit/Feedback/Modal/confirm.js","size":1389},{"name":"Kit/Feedback/Progress/theme.js","size":235},{"name":"Kit/Feedback/SnackBar/SnackBar.js","size":3340},{"name":"Kit/Navigation/Breadcrumb/theme.js","size":274},{"name":"Kit/Navigation/DropDown/style.js","size":1807},{"name":"Kit/Navigation/Header/theme.js","size":230},{"name":"Kit/Navigation/Menu/Menu.js","size":3216},{"name":"Kit/Navigation/Menu/ItemMenu.js","size":6028},{"name":"Kit/Navigation/Pagination/theme.js","size":414},{"name":"Kit/DataEntry/Checkbox/theme.js","size":1156},{"name":"Kit/DataEntry/Radio/theme.js","size":1271},{"name":"Kit/DataEntry/Tag/theme.js","size":406},{"name":"Kit/General/Typography/commons.js","size":933},{"name":"Kit/Feedback/Modal/theme.js","size":975},{"name":"Kit/Feedback/Modal/ConfirmDialog.js","size":3356},{"name":"icons/asn/KitCalendarOutlined.js","size":823},{"name":"icons/asn/KitDeleteOutlined.js","size":839},{"name":"icons/asn/KitDownloadOutlined.js","size":590},{"name":"icons/asn/KitDropdownOutlined.js","size":409},{"name":"icons/asn/KitDropupOutlined.js","size":419},{"name":"icons/asn/KitEditOutlined.js","size":1009},{"name":"icons/asn/KitHideOutlined.js","size":1324},{"name":"icons/asn/KitInfoOutlined.js","size":837},{"name":"icons/asn/KitLessOutlined.js","size":267},{"name":"icons/asn/KitListOutlined.js","size":469},{"name":"icons/asn/KitLockOutlined.js","size":642},{"name":"icons/asn/KitLogoutOutlined.js","size":729},{"name":"icons/asn/KitPdfOutlined.js","size":1635},{"name":"icons/asn/KitPlusOutlined.js","size":462},{"name":"icons/asn/KitRailroadOutlined.js","size":957},{"name":"icons/asn/KitShowOutlined.js","size":1000},{"name":"icons/asn/KitWarningOutlined.js","size":601}],"chunks":[{"id":"index","entry":true,"initial":true,"files":["index.js"],"names":["index"]},{"id":"Kit/App/index","entry":false,"initial":true,"files":["Kit/App/index.js"],"names":["Kit/App/index"]},{"id":"Kit/DataDisplay/Avatar/index","entry":false,"initial":true,"files":["Kit/DataDisplay/Avatar/index.js"],"names":["Kit/DataDisplay/Avatar/index"]},{"id":"Kit/DataDisplay/Badge/index","entry":false,"initial":true,"files":["Kit/DataDisplay/Badge/index.js"],"names":["Kit/DataDisplay/Badge/index"]},{"id":"Kit/DataDisplay/Card/index","entry":false,"initial":true,"files":["Kit/DataDisplay/Card/index.js"],"names":["Kit/DataDisplay/Card/index"]},{"id":"Kit/DataDisplay/Collapse/index","entry":false,"initial":true,"files":["Kit/DataDisplay/Collapse/index.js"],"names":["Kit/DataDisplay/Collapse/index"]},{"id":"Kit/DataDisplay/Image/index","entry":false,"initial":true,"files":["Kit/DataDisplay/Image/index.js"],"names":["Kit/DataDisplay/Image/index"]},{"id":"Kit/DataDisplay/ItemList/index","entry":false,"initial":true,"files":["Kit/DataDisplay/ItemList/index.js"],"names":["Kit/DataDisplay/ItemList/index"]},{"id":"Kit/DataDisplay/Tooltip/index","entry":false,"initial":true,"files":["Kit/DataDisplay/Tooltip/index.js"],"names":["Kit/DataDisplay/Tooltip/index"]},{"id":"Kit/DataDisplay/Tree/index","entry":false,"initial":true,"files":["Kit/DataDisplay/Tree/index.js"],"names":["Kit/DataDisplay/Tree/index"]},{"id":"Kit/DataEntry/Checkbox/index","entry":false,"initial":true,"files":["Kit/DataEntry/Checkbox/index.js"],"names":["Kit/DataEntry/Checkbox/index"]},{"id":"Kit/DataEntry/Input/index","entry":false,"initial":true,"files":["Kit/DataEntry/Input/index.js"],"names":["Kit/DataEntry/Input/index"]},{"id":"Kit/DataEntry/InputNumber/index","entry":false,"initial":true,"files":["Kit/DataEntry/InputNumber/index.js"],"names":["Kit/DataEntry/InputNumber/index"]},{"id":"Kit/DataEntry/Radio/index","entry":false,"initial":true,"files":["Kit/DataEntry/Radio/index.js"],"names":["Kit/DataEntry/Radio/index"]},{"id":"Kit/DataEntry/Rate/index","entry":false,"initial":true,"files":["Kit/DataEntry/Rate/index.js"],"names":["Kit/DataEntry/Rate/index"]},{"id":"Kit/DataEntry/Select/index","entry":false,"initial":true,"files":["Kit/DataEntry/Select/index.js"],"names":["Kit/DataEntry/Select/index"]},{"id":"Kit/DataEntry/Tag/index","entry":false,"initial":true,"files":["Kit/DataEntry/Tag/index.js"],"names":["Kit/DataEntry/Tag/index"]},{"id":"Kit/DataEntry/Switch/index","entry":false,"initial":true,"files":["Kit/DataEntry/Switch/index.js"],"names":["Kit/DataEntry/Switch/index"]},{"id":"Kit/Feedback/Alert/index","entry":false,"initial":true,"files":["Kit/Feedback/Alert/index.js"],"names":["Kit/Feedback/Alert/index"]},{"id":"Kit/Feedback/Modal/index","entry":false,"initial":true,"files":["Kit/Feedback/Modal/index.js"],"names":["Kit/Feedback/Modal/index"]},{"id":"Kit/Feedback/Progress/index","entry":false,"initial":true,"files":["Kit/Feedback/Progress/index.js"],"names":["Kit/Feedback/Progress/index"]},{"id":"Kit/Feedback/SnackBar/index","entry":false,"initial":true,"files":["Kit/Feedback/SnackBar/index.js"],"names":["Kit/Feedback/SnackBar/index"]},{"id":"Kit/General/Button/index","entry":false,"initial":true,"files":["Kit/General/Button/index.js"],"names":["Kit/General/Button/index"]},{"id":"Kit/General/Typography/index","entry":false,"initial":true,"files":["Kit/General/Typography/index.js"],"names":["Kit/General/Typography/index"]},{"id":"Kit/General/Icon/index","entry":false,"initial":true,"files":["Kit/General/Icon/index.js"],"names":["Kit/General/Icon/index"]},{"id":"Kit/Layout/Divider/index","entry":false,"initial":true,"files":["Kit/Layout/Divider/index.js"],"names":["Kit/Layout/Divider/index"]},{"id":"Kit/Layout/Grid/index","entry":false,"initial":true,"files":["Kit/Layout/Grid/index.js"],"names":["Kit/Layout/Grid/index"]},{"id":"Kit/Layout/Space/index","entry":false,"initial":true,"files":["Kit/Layout/Space/index.js"],"names":["Kit/Layout/Space/index"]},{"id":"Kit/Navigation/Breadcrumb/index","entry":false,"initial":true,"files":["Kit/Navigation/Breadcrumb/index.js"],"names":["Kit/Navigation/Breadcrumb/index"]},{"id":"Kit/Navigation/DropDown/index","entry":false,"initial":true,"files":["Kit/Navigation/DropDown/index.js"],"names":["Kit/Navigation/DropDown/index"]},{"id":"Kit/Navigation/Header/index","entry":false,"initial":true,"files":["Kit/Navigation/Header/index.js"],"names":["Kit/Navigation/Header/index"]},{"id":"Kit/Navigation/Menu/index","entry":false,"initial":true,"files":["Kit/Navigation/Menu/index.js"],"names":["Kit/Navigation/Menu/index"]},{"id":"Kit/Navigation/Steps/index","entry":false,"initial":true,"files":["Kit/Navigation/Steps/index.js"],"names":["Kit/Navigation/Steps/index"]},{"id":"Kit/Navigation/Pagination/index","entry":false,"initial":true,"files":["Kit/Navigation/Pagination/index.js"],"names":["Kit/Navigation/Pagination/index"]},{"id":"theme/index","entry":false,"initial":true,"files":["theme/index.js"],"names":["theme/index"]},{"id":"theme/typography","entry":false,"initial":true,"files":["theme/typography.js"],"names":["theme/typography"]},{"id":"theme/colors","entry":false,"initial":true,"files":["theme/colors.js"],"names":["theme/colors"]},{"id":"Kit/DataEntry/Select/style","entry":false,"initial":true,"files":["Kit/DataEntry/Select/style.js"],"names":["Kit/DataEntry/Select/style"]},{"id":"Kit/Feedback/SnackBar/SnackBarProvider","entry":false,"initial":true,"files":["Kit/Feedback/SnackBar/SnackBarProvider.js"],"names":["Kit/Feedback/SnackBar/SnackBarProvider"]},{"id":"Kit/App/style","entry":false,"initial":true,"files":["Kit/App/style.js"],"names":["Kit/App/style"]},{"id":"Kit/DataDisplay/Avatar/Avatar","entry":false,"initial":true,"files":["Kit/DataDisplay/Avatar/Avatar.js"],"names":["Kit/DataDisplay/Avatar/Avatar"]},{"id":"Kit/DataDisplay/Avatar/AvatarGroup","entry":false,"initial":true,"files":["Kit/DataDisplay/Avatar/AvatarGroup.js"],"names":["Kit/DataDisplay/Avatar/AvatarGroup"]},{"id":"Kit/DataDisplay/Card/theme","entry":false,"initial":true,"files":["Kit/DataDisplay/Card/theme.js"],"names":["Kit/DataDisplay/Card/theme"]},{"id":"Kit/DataDisplay/Card/ColorBar","entry":false,"initial":true,"files":["Kit/DataDisplay/Card/ColorBar.js"],"names":["Kit/DataDisplay/Card/ColorBar"]},{"id":"Kit/DataDisplay/Image/theme","entry":false,"initial":true,"files":["Kit/DataDisplay/Image/theme.js"],"names":["Kit/DataDisplay/Image/theme"]},{"id":"Kit/DataEntry/Select/theme","entry":false,"initial":true,"files":["Kit/DataEntry/Select/theme.js"],"names":["Kit/DataEntry/Select/theme"]},{"id":"fonts/Inter-roman.var.woff2","entry":false,"initial":true,"files":["fonts/Inter-roman.var.woff2.js"],"names":["fonts/Inter-roman.var.woff2"]},{"id":"fonts/Inter-italic.var.woff2","entry":false,"initial":true,"files":["fonts/Inter-italic.var.woff2.js"],"names":["fonts/Inter-italic.var.woff2"]},{"id":"Kit/DataEntry/Checkbox/Checkbox","entry":false,"initial":true,"files":["Kit/DataEntry/Checkbox/Checkbox.js"],"names":["Kit/DataEntry/Checkbox/Checkbox"]},{"id":"Kit/DataEntry/Checkbox/Group","entry":false,"initial":true,"files":["Kit/DataEntry/Checkbox/Group.js"],"names":["Kit/DataEntry/Checkbox/Group"]},{"id":"Kit/DataEntry/Input/Input","entry":false,"initial":true,"files":["Kit/DataEntry/Input/Input.js"],"names":["Kit/DataEntry/Input/Input"]},{"id":"Kit/DataEntry/Input/TextArea","entry":false,"initial":true,"files":["Kit/DataEntry/Input/TextArea.js"],"names":["Kit/DataEntry/Input/TextArea"]},{"id":"Kit/DataEntry/Input/Password","entry":false,"initial":true,"files":["Kit/DataEntry/Input/Password.js"],"names":["Kit/DataEntry/Input/Password"]},{"id":"Kit/DataEntry/Radio/Group","entry":false,"initial":true,"files":["Kit/DataEntry/Radio/Group.js"],"names":["Kit/DataEntry/Radio/Group"]},{"id":"Kit/DataEntry/Radio/Radio","entry":false,"initial":true,"files":["Kit/DataEntry/Radio/Radio.js"],"names":["Kit/DataEntry/Radio/Radio"]},{"id":"icons/KitCalendarOutlined","entry":false,"initial":true,"files":["icons/KitCalendarOutlined.js"],"names":["icons/KitCalendarOutlined"]},{"id":"icons/KitDeleteOutlined","entry":false,"initial":true,"files":["icons/KitDeleteOutlined.js"],"names":["icons/KitDeleteOutlined"]},{"id":"icons/KitDownloadOutlined","entry":false,"initial":true,"files":["icons/KitDownloadOutlined.js"],"names":["icons/KitDownloadOutlined"]},{"id":"icons/KitDropdownOutlined","entry":false,"initial":true,"files":["icons/KitDropdownOutlined.js"],"names":["icons/KitDropdownOutlined"]},{"id":"icons/KitDropupOutlined","entry":false,"initial":true,"files":["icons/KitDropupOutlined.js"],"names":["icons/KitDropupOutlined"]},{"id":"icons/KitEditOutlined","entry":false,"initial":true,"files":["icons/KitEditOutlined.js"],"names":["icons/KitEditOutlined"]},{"id":"icons/KitHideOutlined","entry":false,"initial":true,"files":["icons/KitHideOutlined.js"],"names":["icons/KitHideOutlined"]},{"id":"icons/KitInfoOutlined","entry":false,"initial":true,"files":["icons/KitInfoOutlined.js"],"names":["icons/KitInfoOutlined"]},{"id":"icons/KitLessOutlined","entry":false,"initial":true,"files":["icons/KitLessOutlined.js"],"names":["icons/KitLessOutlined"]},{"id":"icons/KitListOutlined","entry":false,"initial":true,"files":["icons/KitListOutlined.js"],"names":["icons/KitListOutlined"]},{"id":"icons/KitLockOutlined","entry":false,"initial":true,"files":["icons/KitLockOutlined.js"],"names":["icons/KitLockOutlined"]},{"id":"icons/KitLogoutOutlined","entry":false,"initial":true,"files":["icons/KitLogoutOutlined.js"],"names":["icons/KitLogoutOutlined"]},{"id":"icons/KitPdfOutlined","entry":false,"initial":true,"files":["icons/KitPdfOutlined.js"],"names":["icons/KitPdfOutlined"]},{"id":"icons/KitPlusOutlined","entry":false,"initial":true,"files":["icons/KitPlusOutlined.js"],"names":["icons/KitPlusOutlined"]},{"id":"icons/KitRailroadOutlined","entry":false,"initial":true,"files":["icons/KitRailroadOutlined.js"],"names":["icons/KitRailroadOutlined"]},{"id":"icons/KitShowOutlined","entry":false,"initial":true,"files":["icons/KitShowOutlined.js"],"names":["icons/KitShowOutlined"]},{"id":"icons/KitWarningOutlined","entry":false,"initial":true,"files":["icons/KitWarningOutlined.js"],"names":["icons/KitWarningOutlined"]},{"id":"Kit/DataEntry/Tag/Tag","entry":false,"initial":true,"files":["Kit/DataEntry/Tag/Tag.js"],"names":["Kit/DataEntry/Tag/Tag"]},{"id":"Kit/DataEntry/Tag/TagInput","entry":false,"initial":true,"files":["Kit/DataEntry/Tag/TagInput.js"],"names":["Kit/DataEntry/Tag/TagInput"]},{"id":"Kit/DataEntry/Switch/theme","entry":false,"initial":true,"files":["Kit/DataEntry/Switch/theme.js"],"names":["Kit/DataEntry/Switch/theme"]},{"id":"Kit/General/Button/theme","entry":false,"initial":true,"files":["Kit/General/Button/theme.js"],"names":["Kit/General/Button/theme"]},{"id":"Kit/General/Typography/Title","entry":false,"initial":true,"files":["Kit/General/Typography/Title.js"],"names":["Kit/General/Typography/Title"]},{"id":"Kit/General/Typography/Text","entry":false,"initial":true,"files":["Kit/General/Typography/Text.js"],"names":["Kit/General/Typography/Text"]},{"id":"Kit/General/Typography/Link","entry":false,"initial":true,"files":["Kit/General/Typography/Link.js"],"names":["Kit/General/Typography/Link"]},{"id":"Kit/General/Typography/Paragraph","entry":false,"initial":true,"files":["Kit/General/Typography/Paragraph.js"],"names":["Kit/General/Typography/Paragraph"]},{"id":"Kit/General/Icon/theme","entry":false,"initial":true,"files":["Kit/General/Icon/theme.js"],"names":["Kit/General/Icon/theme"]},{"id":"Kit/Layout/Grid/Row","entry":false,"initial":true,"files":["Kit/Layout/Grid/Row.js"],"names":["Kit/Layout/Grid/Row"]},{"id":"Kit/Layout/Grid/Col","entry":false,"initial":true,"files":["Kit/Layout/Grid/Col.js"],"names":["Kit/Layout/Grid/Col"]},{"id":"Kit/Layout/Space/theme","entry":false,"initial":true,"files":["Kit/Layout/Space/theme.js"],"names":["Kit/Layout/Space/theme"]},{"id":"Kit/Feedback/Modal/Modal","entry":false,"initial":true,"files":["Kit/Feedback/Modal/Modal.js"],"names":["Kit/Feedback/Modal/Modal"]},{"id":"Kit/Feedback/Modal/confirm","entry":false,"initial":true,"files":["Kit/Feedback/Modal/confirm.js"],"names":["Kit/Feedback/Modal/confirm"]},{"id":"Kit/Feedback/Progress/theme","entry":false,"initial":true,"files":["Kit/Feedback/Progress/theme.js"],"names":["Kit/Feedback/Progress/theme"]},{"id":"Kit/Feedback/SnackBar/SnackBar","entry":false,"initial":true,"files":["Kit/Feedback/SnackBar/SnackBar.js"],"names":["Kit/Feedback/SnackBar/SnackBar"]},{"id":"Kit/Navigation/Breadcrumb/theme","entry":false,"initial":true,"files":["Kit/Navigation/Breadcrumb/theme.js"],"names":["Kit/Navigation/Breadcrumb/theme"]},{"id":"Kit/Navigation/DropDown/style","entry":false,"initial":true,"files":["Kit/Navigation/DropDown/style.js"],"names":["Kit/Navigation/DropDown/style"]},{"id":"Kit/Navigation/Header/theme","entry":false,"initial":true,"files":["Kit/Navigation/Header/theme.js"],"names":["Kit/Navigation/Header/theme"]},{"id":"Kit/Navigation/Menu/Menu","entry":false,"initial":true,"files":["Kit/Navigation/Menu/Menu.js"],"names":["Kit/Navigation/Menu/Menu"]},{"id":"Kit/Navigation/Menu/ItemMenu","entry":false,"initial":true,"files":["Kit/Navigation/Menu/ItemMenu.js"],"names":["Kit/Navigation/Menu/ItemMenu"]},{"id":"Kit/Navigation/Pagination/theme","entry":false,"initial":true,"files":["Kit/Navigation/Pagination/theme.js"],"names":["Kit/Navigation/Pagination/theme"]},{"id":"Kit/DataEntry/Checkbox/theme","entry":false,"initial":true,"files":["Kit/DataEntry/Checkbox/theme.js"],"names":["Kit/DataEntry/Checkbox/theme"]},{"id":"Kit/DataEntry/Radio/theme","entry":false,"initial":true,"files":["Kit/DataEntry/Radio/theme.js"],"names":["Kit/DataEntry/Radio/theme"]},{"id":"Kit/DataEntry/Tag/theme","entry":false,"initial":true,"files":["Kit/DataEntry/Tag/theme.js"],"names":["Kit/DataEntry/Tag/theme"]},{"id":"Kit/General/Typography/commons","entry":false,"initial":true,"files":["Kit/General/Typography/commons.js"],"names":["Kit/General/Typography/commons"]},{"id":"Kit/Feedback/Modal/theme","entry":false,"initial":true,"files":["Kit/Feedback/Modal/theme.js"],"names":["Kit/Feedback/Modal/theme"]},{"id":"Kit/Feedback/Modal/ConfirmDialog","entry":false,"initial":true,"files":["Kit/Feedback/Modal/ConfirmDialog.js"],"names":["Kit/Feedback/Modal/ConfirmDialog"]},{"id":"icons/asn/KitCalendarOutlined","entry":false,"initial":true,"files":["icons/asn/KitCalendarOutlined.js"],"names":["icons/asn/KitCalendarOutlined"]},{"id":"icons/asn/KitDeleteOutlined","entry":false,"initial":true,"files":["icons/asn/KitDeleteOutlined.js"],"names":["icons/asn/KitDeleteOutlined"]},{"id":"icons/asn/KitDownloadOutlined","entry":false,"initial":true,"files":["icons/asn/KitDownloadOutlined.js"],"names":["icons/asn/KitDownloadOutlined"]},{"id":"icons/asn/KitDropdownOutlined","entry":false,"initial":true,"files":["icons/asn/KitDropdownOutlined.js"],"names":["icons/asn/KitDropdownOutlined"]},{"id":"icons/asn/KitDropupOutlined","entry":false,"initial":true,"files":["icons/asn/KitDropupOutlined.js"],"names":["icons/asn/KitDropupOutlined"]},{"id":"icons/asn/KitEditOutlined","entry":false,"initial":true,"files":["icons/asn/KitEditOutlined.js"],"names":["icons/asn/KitEditOutlined"]},{"id":"icons/asn/KitHideOutlined","entry":false,"initial":true,"files":["icons/asn/KitHideOutlined.js"],"names":["icons/asn/KitHideOutlined"]},{"id":"icons/asn/KitInfoOutlined","entry":false,"initial":true,"files":["icons/asn/KitInfoOutlined.js"],"names":["icons/asn/KitInfoOutlined"]},{"id":"icons/asn/KitLessOutlined","entry":false,"initial":true,"files":["icons/asn/KitLessOutlined.js"],"names":["icons/asn/KitLessOutlined"]},{"id":"icons/asn/KitListOutlined","entry":false,"initial":true,"files":["icons/asn/KitListOutlined.js"],"names":["icons/asn/KitListOutlined"]},{"id":"icons/asn/KitLockOutlined","entry":false,"initial":true,"files":["icons/asn/KitLockOutlined.js"],"names":["icons/asn/KitLockOutlined"]},{"id":"icons/asn/KitLogoutOutlined","entry":false,"initial":true,"files":["icons/asn/KitLogoutOutlined.js"],"names":["icons/asn/KitLogoutOutlined"]},{"id":"icons/asn/KitPdfOutlined","entry":false,"initial":true,"files":["icons/asn/KitPdfOutlined.js"],"names":["icons/asn/KitPdfOutlined"]},{"id":"icons/asn/KitPlusOutlined","entry":false,"initial":true,"files":["icons/asn/KitPlusOutlined.js"],"names":["icons/asn/KitPlusOutlined"]},{"id":"icons/asn/KitRailroadOutlined","entry":false,"initial":true,"files":["icons/asn/KitRailroadOutlined.js"],"names":["icons/asn/KitRailroadOutlined"]},{"id":"icons/asn/KitShowOutlined","entry":false,"initial":true,"files":["icons/asn/KitShowOutlined.js"],"names":["icons/asn/KitShowOutlined"]},{"id":"icons/asn/KitWarningOutlined","entry":false,"initial":true,"files":["icons/asn/KitWarningOutlined.js"],"names":["icons/asn/KitWarningOutlined"]}],"modules":[{"name":"./src/index.tsx","size":0,"chunks":["index"]},{"name":"./src/Kit/App/index.tsx","size":334,"chunks":["Kit/App/index"]},{"name":"./src/Kit/DataDisplay/Avatar/index.tsx","size":101,"chunks":["Kit/DataDisplay/Avatar/index"]},{"name":"./src/Kit/DataDisplay/Badge/index.tsx","size":1838,"chunks":["Kit/DataDisplay/Badge/index"]},{"name":"./src/Kit/DataDisplay/Card/index.tsx","size":10162,"chunks":["Kit/DataDisplay/Card/index"]},{"name":"./src/Kit/DataDisplay/Collapse/index.tsx","size":220,"chunks":["Kit/DataDisplay/Collapse/index"]},{"name":"./src/Kit/DataDisplay/Image/index.tsx","size":707,"chunks":["Kit/DataDisplay/Image/index"]},{"name":"./src/Kit/DataDisplay/ItemList/index.tsx","size":9034,"chunks":["Kit/DataDisplay/ItemList/index"]},{"name":"./src/Kit/DataDisplay/Tooltip/index.tsx","size":165,"chunks":["Kit/DataDisplay/Tooltip/index"]},{"name":"./src/Kit/DataDisplay/Tree/index.tsx","size":4671,"chunks":["Kit/DataDisplay/Tree/index"]},{"name":"./src/Kit/DataEntry/Checkbox/index.tsx","size":102,"chunks":["Kit/DataEntry/Checkbox/index"]},{"name":"./src/Kit/DataEntry/Input/index.tsx","size":129,"chunks":["Kit/DataEntry/Input/index"]},{"name":"./src/Kit/DataEntry/InputNumber/index.tsx","size":2653,"chunks":["Kit/DataEntry/InputNumber/index"]},{"name":"./src/Kit/DataEntry/Radio/index.tsx","size":87,"chunks":["Kit/DataEntry/Radio/index"]},{"name":"./src/Kit/DataEntry/Rate/index.tsx","size":676,"chunks":["Kit/DataEntry/Rate/index"]},{"name":"./src/Kit/DataEntry/Select/index.tsx","size":3028,"chunks":["Kit/DataEntry/Select/index"]},{"name":"./src/Kit/DataEntry/Tag/index.tsx","size":83,"chunks":["Kit/DataEntry/Tag/index"]},{"name":"./src/Kit/DataEntry/Switch/index.tsx","size":2021,"chunks":["Kit/DataEntry/Switch/index"]},{"name":"./src/Kit/Feedback/Alert/index.tsx","size":1421,"chunks":["Kit/Feedback/Alert/index"]},{"name":"./src/Kit/Feedback/Modal/index.tsx","size":480,"chunks":["Kit/Feedback/Modal/index"]},{"name":"./src/Kit/Feedback/Progress/index.tsx","size":368,"chunks":["Kit/Feedback/Progress/index"]},{"name":"./src/Kit/Feedback/SnackBar/index.tsx","size":185,"chunks":["Kit/Feedback/SnackBar/index"]},{"name":"./src/Kit/General/Button/index.tsx","size":9410,"chunks":["Kit/General/Button/index"]},{"name":"./src/Kit/General/Typography/index.tsx","size":150,"chunks":["Kit/General/Typography/index"]},{"name":"./src/Kit/General/Icon/index.tsx","size":1204,"chunks":["Kit/General/Icon/index"]},{"name":"./src/Kit/Layout/Divider/index.tsx","size":637,"chunks":["Kit/Layout/Divider/index"]},{"name":"./src/Kit/Layout/Grid/index.tsx","size":82,"chunks":["Kit/Layout/Grid/index"]},{"name":"./src/Kit/Layout/Space/index.tsx","size":473,"chunks":["Kit/Layout/Space/index"]},{"name":"./src/Kit/Navigation/Breadcrumb/index.tsx","size":490,"chunks":["Kit/Navigation/Breadcrumb/index"]},{"name":"./src/Kit/Navigation/DropDown/index.tsx","size":348,"chunks":["Kit/Navigation/DropDown/index"]},{"name":"./src/Kit/Navigation/Header/index.tsx","size":3415,"chunks":["Kit/Navigation/Header/index"]},{"name":"./src/Kit/Navigation/Menu/index.tsx","size":87,"chunks":["Kit/Navigation/Menu/index"]},{"name":"./src/Kit/Navigation/Steps/index.tsx","size":795,"chunks":["Kit/Navigation/Steps/index"]},{"name":"./src/Kit/Navigation/Pagination/index.tsx","size":3573,"chunks":["Kit/Navigation/Pagination/index"]},{"name":"./src/theme/index.ts","size":7236,"chunks":["theme/index"]},{"name":"./src/theme/typography.ts","size":618,"chunks":["theme/typography"]},{"name":"./src/theme/colors.ts","size":2074,"chunks":["theme/colors"]},{"name":"./src/Kit/DataEntry/Select/style.tsx","size":8712,"chunks":["Kit/DataEntry/Select/style"]},{"name":"./src/Kit/Feedback/SnackBar/SnackBarProvider.tsx","size":409,"chunks":["Kit/Feedback/SnackBar/SnackBarProvider"]},{"name":"./src/Kit/App/style.ts","size":580,"chunks":["Kit/App/style"]},{"name":"./src/Kit/DataDisplay/Avatar/Avatar.tsx","size":761,"chunks":["Kit/DataDisplay/Avatar/Avatar"]},{"name":"./src/Kit/DataDisplay/Avatar/AvatarGroup.tsx","size":379,"chunks":["Kit/DataDisplay/Avatar/AvatarGroup"]},{"name":"./src/Kit/DataDisplay/Card/theme.ts","size":1101,"chunks":["Kit/DataDisplay/Card/theme"]},{"name":"./src/Kit/DataDisplay/Card/ColorBar.tsx","size":960,"chunks":["Kit/DataDisplay/Card/ColorBar"]},{"name":"./src/Kit/DataDisplay/Image/theme.ts","size":96,"chunks":["Kit/DataDisplay/Image/theme"]},{"name":"./src/Kit/DataEntry/Select/theme.ts","size":1542,"chunks":["Kit/DataEntry/Select/theme"]},{"name":"./src/fonts/Inter-roman.var.woff2","size":302953,"chunks":["fonts/Inter-roman.var.woff2"]},{"name":"./src/fonts/Inter-italic.var.woff2","size":326762,"chunks":["fonts/Inter-italic.var.woff2"]},{"name":"./src/Kit/DataEntry/Checkbox/Checkbox.tsx","size":3409,"chunks":["Kit/DataEntry/Checkbox/Checkbox"]},{"name":"./src/Kit/DataEntry/Checkbox/Group.tsx","size":3088,"chunks":["Kit/DataEntry/Checkbox/Group"]},{"name":"./src/Kit/DataEntry/Input/Input.tsx","size":4287,"chunks":["Kit/DataEntry/Input/Input"]},{"name":"./src/Kit/DataEntry/Input/TextArea.tsx","size":3990,"chunks":["Kit/DataEntry/Input/TextArea"]},{"name":"./src/Kit/DataEntry/Input/Password.tsx","size":3985,"chunks":["Kit/DataEntry/Input/Password"]},{"name":"./src/Kit/DataEntry/Radio/Group.tsx","size":2746,"chunks":["Kit/DataEntry/Radio/Group"]},{"name":"./src/Kit/DataEntry/Radio/Radio.tsx","size":3522,"chunks":["Kit/DataEntry/Radio/Radio"]},{"name":"./src/icons/KitCalendarOutlined.tsx","size":213,"chunks":["icons/KitCalendarOutlined"]},{"name":"./src/icons/KitDeleteOutlined.tsx","size":205,"chunks":["icons/KitDeleteOutlined"]},{"name":"./src/icons/KitDownloadOutlined.tsx","size":213,"chunks":["icons/KitDownloadOutlined"]},{"name":"./src/icons/KitDropdownOutlined.tsx","size":213,"chunks":["icons/KitDropdownOutlined"]},{"name":"./src/icons/KitDropupOutlined.tsx","size":205,"chunks":["icons/KitDropupOutlined"]},{"name":"./src/icons/KitEditOutlined.tsx","size":197,"chunks":["icons/KitEditOutlined"]},{"name":"./src/icons/KitHideOutlined.tsx","size":197,"chunks":["icons/KitHideOutlined"]},{"name":"./src/icons/KitInfoOutlined.tsx","size":197,"chunks":["icons/KitInfoOutlined"]},{"name":"./src/icons/KitLessOutlined.tsx","size":197,"chunks":["icons/KitLessOutlined"]},{"name":"./src/icons/KitListOutlined.tsx","size":197,"chunks":["icons/KitListOutlined"]},{"name":"./src/icons/KitLockOutlined.tsx","size":197,"chunks":["icons/KitLockOutlined"]},{"name":"./src/icons/KitLogoutOutlined.tsx","size":205,"chunks":["icons/KitLogoutOutlined"]},{"name":"./src/icons/KitPdfOutlined.tsx","size":193,"chunks":["icons/KitPdfOutlined"]},{"name":"./src/icons/KitPlusOutlined.tsx","size":197,"chunks":["icons/KitPlusOutlined"]},{"name":"./src/icons/KitRailroadOutlined.tsx","size":213,"chunks":["icons/KitRailroadOutlined"]},{"name":"./src/icons/KitShowOutlined.tsx","size":197,"chunks":["icons/KitShowOutlined"]},{"name":"./src/icons/KitWarningOutlined.tsx","size":209,"chunks":["icons/KitWarningOutlined"]},{"name":"./src/Kit/DataEntry/Tag/Tag.tsx","size":2553,"chunks":["Kit/DataEntry/Tag/Tag"]},{"name":"./src/Kit/DataEntry/Tag/TagInput.tsx","size":2712,"chunks":["Kit/DataEntry/Tag/TagInput"]},{"name":"./src/Kit/DataEntry/Switch/theme.ts","size":1029,"chunks":["Kit/DataEntry/Switch/theme"]},{"name":"./src/Kit/General/Button/theme.ts","size":9492,"chunks":["Kit/General/Button/theme"]},{"name":"./src/Kit/General/Typography/Title.tsx","size":2059,"chunks":["Kit/General/Typography/Title"]},{"name":"./src/Kit/General/Typography/Text.tsx","size":994,"chunks":["Kit/General/Typography/Text"]},{"name":"./src/Kit/General/Typography/Link.tsx","size":994,"chunks":["Kit/General/Typography/Link"]},{"name":"./src/Kit/General/Typography/Paragraph.tsx","size":1014,"chunks":["Kit/General/Typography/Paragraph"]},{"name":"./src/Kit/General/Icon/theme.ts","size":294,"chunks":["Kit/General/Icon/theme"]},{"name":"./src/Kit/Layout/Grid/Row.tsx","size":110,"chunks":["Kit/Layout/Grid/Row"]},{"name":"./src/Kit/Layout/Grid/Col.tsx","size":110,"chunks":["Kit/Layout/Grid/Col"]},{"name":"./src/Kit/Layout/Space/theme.ts","size":65,"chunks":["Kit/Layout/Space/theme"]},{"name":"./src/Kit/Feedback/Modal/Modal.tsx","size":3949,"chunks":["Kit/Feedback/Modal/Modal"]},{"name":"./src/Kit/Feedback/Modal/confirm.tsx","size":1837,"chunks":["Kit/Feedback/Modal/confirm"]},{"name":"./src/Kit/Feedback/Progress/theme.ts","size":125,"chunks":["Kit/Feedback/Progress/theme"]},{"name":"./src/Kit/Feedback/SnackBar/SnackBar.tsx","size":3752,"chunks":["Kit/Feedback/SnackBar/SnackBar"]},{"name":"./src/Kit/Navigation/Breadcrumb/theme.ts","size":249,"chunks":["Kit/Navigation/Breadcrumb/theme"]},{"name":"./src/Kit/Navigation/DropDown/style.ts","size":1901,"chunks":["Kit/Navigation/DropDown/style"]},{"name":"./src/Kit/Navigation/Header/theme.ts","size":189,"chunks":["Kit/Navigation/Header/theme"]},{"name":"./src/Kit/Navigation/Menu/Menu.tsx","size":3974,"chunks":["Kit/Navigation/Menu/Menu"]},{"name":"./src/Kit/Navigation/Menu/ItemMenu.tsx","size":7064,"chunks":["Kit/Navigation/Menu/ItemMenu"]},{"name":"./src/Kit/Navigation/Pagination/theme.ts","size":399,"chunks":["Kit/Navigation/Pagination/theme"]},{"name":"./src/Kit/DataEntry/Checkbox/theme.ts","size":1372,"chunks":["Kit/DataEntry/Checkbox/theme"]},{"name":"./src/Kit/DataEntry/Radio/theme.ts","size":1505,"chunks":["Kit/DataEntry/Radio/theme"]},{"name":"./src/Kit/DataEntry/Tag/theme.ts","size":387,"chunks":["Kit/DataEntry/Tag/theme"]},{"name":"./src/Kit/General/Typography/commons.ts","size":857,"chunks":["Kit/General/Typography/commons"]},{"name":"./src/Kit/Feedback/Modal/theme.tsx","size":973,"chunks":["Kit/Feedback/Modal/theme"]},{"name":"./src/Kit/Feedback/Modal/ConfirmDialog.tsx","size":2991,"chunks":["Kit/Feedback/Modal/ConfirmDialog"]},{"name":"./src/icons/asn/KitCalendarOutlined.ts","size":969,"chunks":["icons/asn/KitCalendarOutlined"]},{"name":"./src/icons/asn/KitDeleteOutlined.ts","size":899,"chunks":["icons/asn/KitDeleteOutlined"]},{"name":"./src/icons/asn/KitDownloadOutlined.ts","size":672,"chunks":["icons/asn/KitDownloadOutlined"]},{"name":"./src/icons/asn/KitDropdownOutlined.ts","size":471,"chunks":["icons/asn/KitDropdownOutlined"]},{"name":"./src/icons/asn/KitDropupOutlined.ts","size":479,"chunks":["icons/asn/KitDropupOutlined"]},{"name":"./src/icons/asn/KitEditOutlined.ts","size":1151,"chunks":["icons/asn/KitEditOutlined"]},{"name":"./src/icons/asn/KitHideOutlined.ts","size":1466,"chunks":["icons/asn/KitHideOutlined"]},{"name":"./src/icons/asn/KitInfoOutlined.ts","size":1113,"chunks":["icons/asn/KitInfoOutlined"]},{"name":"./src/icons/asn/KitLessOutlined.ts","size":273,"chunks":["icons/asn/KitLessOutlined"]},{"name":"./src/icons/asn/KitListOutlined.ts","size":527,"chunks":["icons/asn/KitListOutlined"]},{"name":"./src/icons/asn/KitLockOutlined.ts","size":700,"chunks":["icons/asn/KitLockOutlined"]},{"name":"./src/icons/asn/KitLogoutOutlined.ts","size":789,"chunks":["icons/asn/KitLogoutOutlined"]},{"name":"./src/icons/asn/KitPdfOutlined.ts","size":1692,"chunks":["icons/asn/KitPdfOutlined"]},{"name":"./src/icons/asn/KitPlusOutlined.ts","size":520,"chunks":["icons/asn/KitPlusOutlined"]},{"name":"./src/icons/asn/KitRailroadOutlined.ts","size":1103,"chunks":["icons/asn/KitRailroadOutlined"]},{"name":"./src/icons/asn/KitShowOutlined.ts","size":1142,"chunks":["icons/asn/KitShowOutlined"]},{"name":"./src/icons/asn/KitWarningOutlined.ts","size":662,"chunks":["icons/asn/KitWarningOutlined"]}]}